comet_maths/__init__.py
comet_maths/_version.py
comet_maths/generate_sample/__init__.py
comet_maths/generate_sample/generate_sample.py
comet_maths/generate_sample/probability_density_function.py
comet_maths/generate_sample/tests/__init__.py
comet_maths/generate_sample/tests/test_generate_sample.py
comet_maths/interpolation/__init__.py
comet_maths/interpolation/interpolation.py
comet_maths/interpolation/tests/__init__.py
comet_maths/interpolation/tests/test_interpolation.py
comet_maths/linear_algebra/__init__.py
comet_maths/linear_algebra/matrix_calculation.py
comet_maths/linear_algebra/matrix_conversion.py
comet_maths/linear_algebra/tests/__init__.py
comet_maths/linear_algebra/tests/test_matrix_calculation.py
comet_maths/linear_algebra/tests/test_matrix_conversion.py
comet_maths-1.0.8.dist-info/licenses/LICENSE
comet_maths-1.0.8.dist-info/METADATA
comet_maths-1.0.8.dist-info/WHEEL
comet_maths-1.0.8.dist-info/top_level.txt
comet_maths-1.0.8.dist-info/RECORD
