Metadata-Version: 2.4
Name: comet_maths
Version: 1.0.8
Summary: Mathematical algorithms and tools to use within CoMet toolkit.
Home-page: https://github.com/comet-toolkit/comet_maths
Author: CoMet Toolkit Team
Author-email: team@comet-toolkit.org
License: LGPLv3
Classifier: Development Status :: 2 - Pre-Alpha
Classifier: Programming Language :: Python
Classifier: Programming Language :: Python :: 3.6
Classifier: Programming Language :: Python :: 3.7
Classifier: Programming Language :: Python :: 3.8
Classifier: Programming Language :: Python :: 3.9
License-File: LICENSE
Requires-Dist: numpy>=2.2.4
Requires-Dist: scikit-learn>=1.6.1
Requires-Dist: numdifftools
Requires-Dist: scipy>=1.15.2
Requires-Dist: matplotlib>=3.10.1
Provides-Extra: dev
Requires-Dist: pre-commit; extra == "dev"
Requires-Dist: tox; extra == "dev"
Requires-Dist: sphinx; extra == "dev"
Requires-Dist: sphinx_design; extra == "dev"
Requires-Dist: sphinx_book_theme; extra == "dev"
Requires-Dist: ipython; extra == "dev"
Requires-Dist: sphinx_autosummary_accessors; extra == "dev"
Provides-Extra: interpolation
Requires-Dist: punpy>=1.0.4; extra == "interpolation"
Dynamic: author
Dynamic: author-email
Dynamic: classifier
Dynamic: description
Dynamic: home-page
Dynamic: license
Dynamic: license-file
Dynamic: provides-extra
Dynamic: requires-dist
Dynamic: summary
